thatsme/__init__.py
thatsme/dados.py
thatsme/pdf.py
thatsme/qrcode.py
thatsme/thatsme.py
thatsme-0.0.3.2.dist-info/LICENSE
thatsme-0.0.3.2.dist-info/METADATA
thatsme-0.0.3.2.dist-info/WHEEL
thatsme-0.0.3.2.dist-info/top_level.txt
thatsme-0.0.3.2.dist-info/RECORD
