Metadata-Version: 2.1
Name: thatsme
Version: 0.0.3.2
Summary: Pacote que gera crachá através do nome de usuário do Github com seus dados (Avatar e Bio) e, qrcode de redes sociais (Facebook, Instagram).
Home-page: https://github.com/WendelSantosNunes/thatsme
Author: Wendel dos Santos Nunes
Author-email: wendelnunes9999@gmail.com
License: UNKNOWN
Platform: UNKNOWN
Classifier: Programming Language :: Python :: 3
Classifier: License :: OSI Approved :: MIT License
Classifier: Operating System :: OS Independent
Requires-Python: >=3.8
License-File: LICENSE
